{
  "$schema": "https://docs.renovatebot.com/renovate-schema.json",
  "description": "Settings for Java libraries",
  "packageRules": [
    {
      "matchCategories": [],
      "matchPackageNames": [
        "@types/node",
        "@tsconfig/node**"
      ],
      "groupName": "@types/node"
    },
    {
      "description": "@octokit/plugin-request-log: group dependencies",
      "matchCategories": [
        "js"
      ],
      "matchPackageNames": [
        "@octokit/plugin-request-log"
      ],
      "groupName": "@octokit/plugin-request-log"
    },
    {
      "description": "@octokit/plugin-retry: group dependencies",
      "matchCategories": [
        "js"
      ],
      "matchPackageNames": [
        "@octokit/plugin-retry"
      ],
      "groupName": "@octokit/plugin-retry"
    },
    {
      "description": "@octokit/plugin-throttling: group dependencies",
      "matchCategories": [
        "js"
      ],
      "matchPackageNames": [
        "@octokit/plugin-throttling"
      ],
      "groupName": "@octokit/plugin-throttling"
    }
  ]
}
